<?xml version="1.0" encoding="UTF-8"?>
<!DOCTYPE mapper PUBLIC "-//mybatis.org//DTD Mapper 3.0//EN" "http://mybatis.org/dtd/mybatis-3-mapper.dtd">
<mapper namespace="com.doushabao.saas.mapper.order.OrderMapper">
  <resultMap id="BaseResultMap" type="com.doushabao.saas.pojo.order.Order">
    <!--
      WARNING - @mbg.generated
      This element is automatically generated by MyBatis Generator, do not modify.
      This element was generated on Mon Jun 04 11:04:34 CST 2018.
    -->
    <id column="id" jdbcType="BIGINT" property="id" />
    <result column="ticket_no" jdbcType="VARCHAR" property="ticketNo" />
    <result column="product_id_list" jdbcType="VARCHAR" property="productIdList" />
    <result column="status" jdbcType="INTEGER" property="status" />
    <result column="original_amount" jdbcType="INTEGER" property="originalAmount" />
    <result column="discount_amount" jdbcType="INTEGER" property="discountAmount" />
    <result column="order_time" jdbcType="TIMESTAMP" property="orderTime" />
    <result column="pay_time" jdbcType="TIMESTAMP" property="payTime" />
    <result column="source" jdbcType="VARCHAR" property="source" />
    <result column="user_id" jdbcType="BIGINT" property="userId" />
    <result column="name" jdbcType="VARCHAR" property="name" />
    <result column="phone_no" jdbcType="VARCHAR" property="phoneNo" />
    <result column="id_card" jdbcType="VARCHAR" property="idCard" />
    <result column="sex" jdbcType="VARCHAR" property="sex" />
    <result column="currency" jdbcType="VARCHAR" property="currency" />
    <result column="is_exit" jdbcType="INTEGER" property="isExit" />
    <result column="order_way" jdbcType="INTEGER" property="orderWay" />
    <result column="excel_batch" jdbcType="VARCHAR" property="excelBatch" />
    <result column="express_no" jdbcType="VARCHAR" property="expressNo" />
    <result column="purchas_order_no" jdbcType="VARCHAR" property="purchasOrderNo" />
    <result column="goods_value" jdbcType="INTEGER" property="goodsValue" />
    <result column="goods_value_detail" jdbcType="VARCHAR" property="goodsValueDetail" />
    <result column="goods_category" jdbcType="VARCHAR" property="goodsCategory" />
    <result column="goods_kind" jdbcType="VARCHAR" property="goodsKind" />
    <result column="goods_weight" jdbcType="DOUBLE" property="goodsWeight" />
    <result column="is_Reinforce" jdbcType="INTEGER" property="isReinforce" />
    <result column="prescription" jdbcType="VARCHAR" property="prescription" />
    <result column="express_mark" jdbcType="VARCHAR" property="expressMark" />
    <result column="express_time" jdbcType="TIMESTAMP" property="expressTime" />
    <result column="express_line" jdbcType="VARCHAR" property="expressLine" />
    <result column="express_channel" jdbcType="VARCHAR" property="expressChannel" />
    <result column="receiver_address" jdbcType="VARCHAR" property="receiverAddress" />
    <result column="loading_port" jdbcType="VARCHAR" property="loadingPort" />
    <result column="destination_port" jdbcType="VARCHAR" property="destinationPort" />
    <result column="border_shopping_site" jdbcType="VARCHAR" property="borderShoppingSite" />
    <result column="shopping_site" jdbcType="VARCHAR" property="shoppingSite" />
    <result column="shopping_time" jdbcType="TIMESTAMP" property="shoppingTime" />
    <result column="premium" jdbcType="INTEGER" property="premium" />
    <result column="create_at" jdbcType="TIMESTAMP" property="createAt" />
    <result column="update_at" jdbcType="TIMESTAMP" property="updateAt" />
  </resultMap>
  <sql id="Example_Where_Clause">
    <!--
      WARNING - @mbg.generated
      This element is automatically generated by MyBatis Generator, do not modify.
      This element was generated on Mon Jun 04 11:04:34 CST 2018.
    -->
    <where>
      <foreach collection="oredCriteria" item="criteria" separator="or">
        <if test="criteria.valid">
          <trim prefix="(" prefixOverrides="and" suffix=")">
            <foreach collection="criteria.criteria" item="criterion">
              <choose>
                <when test="criterion.noValue">
                  and ${criterion.condition}
                </when>
                <when test="criterion.singleValue">
                  and ${criterion.condition} #{criterion.value}
                </when>
                <when test="criterion.betweenValue">
                  and ${criterion.condition} #{criterion.value} and #{criterion.secondValue}
                </when>
                <when test="criterion.listValue">
                  and ${criterion.condition}
                  <foreach close=")" collection="criterion.value" item="listItem" open="(" separator=",">
                    #{listItem}
                  </foreach>
                </when>
              </choose>
            </foreach>
          </trim>
        </if>
      </foreach>
    </where>
  </sql>
  <sql id="Update_By_Example_Where_Clause">
    <!--
      WARNING - @mbg.generated
      This element is automatically generated by MyBatis Generator, do not modify.
      This element was generated on Mon Jun 04 11:04:34 CST 2018.
    -->
    <where>
      <foreach collection="example.oredCriteria" item="criteria" separator="or">
        <if test="criteria.valid">
          <trim prefix="(" prefixOverrides="and" suffix=")">
            <foreach collection="criteria.criteria" item="criterion">
              <choose>
                <when test="criterion.noValue">
                  and ${criterion.condition}
                </when>
                <when test="criterion.singleValue">
                  and ${criterion.condition} #{criterion.value}
                </when>
                <when test="criterion.betweenValue">
                  and ${criterion.condition} #{criterion.value} and #{criterion.secondValue}
                </when>
                <when test="criterion.listValue">
                  and ${criterion.condition}
                  <foreach close=")" collection="criterion.value" item="listItem" open="(" separator=",">
                    #{listItem}
                  </foreach>
                </when>
              </choose>
            </foreach>
          </trim>
        </if>
      </foreach>
    </where>
  </sql>
  <sql id="Base_Column_List">
    <!--
      WARNING - @mbg.generated
      This element is automatically generated by MyBatis Generator, do not modify.
      This element was generated on Mon Jun 04 11:04:34 CST 2018.
    -->
    id, ticket_no, product_id_list, status, original_amount, discount_amount, order_time, 
    pay_time, source, user_id, name, phone_no, id_card, sex, currency, is_exit, order_way, 
    excel_batch, express_no, purchas_order_no, goods_value, goods_value_detail, goods_category, 
    goods_kind, goods_weight, is_Reinforce, prescription, express_mark, express_time, 
    express_line, express_channel, receiver_address, loading_port, destination_port, 
    border_shopping_site, shopping_site, shopping_time, premium, create_at, update_at
  </sql>
  <select id="selectByExample" parameterType="com.doushabao.saas.pojo.order.OrderExample" resultMap="BaseResultMap">
    <!--
      WARNING - @mbg.generated
      This element is automatically generated by MyBatis Generator, do not modify.
      This element was generated on Mon Jun 04 11:04:34 CST 2018.
    -->
    select
    <if test="distinct">
      distinct
    </if>
    <include refid="Base_Column_List" />
    from t_order
    <if test="_parameter != null">
      <include refid="Example_Where_Clause" />
    </if>
    <if test="orderByClause != null">
      order by ${orderByClause}
    </if>
  </select>
  <select id="selectByPrimaryKey" parameterType="java.lang.Long" resultMap="BaseResultMap">
    <!--
      WARNING - @mbg.generated
      This element is automatically generated by MyBatis Generator, do not modify.
      This element was generated on Mon Jun 04 11:04:34 CST 2018.
    -->
    select 
    <include refid="Base_Column_List" />
    from t_order
    where id = #{id,jdbcType=BIGINT}
  </select>
  <delete id="deleteByPrimaryKey" parameterType="java.lang.Long">
    <!--
      WARNING - @mbg.generated
      This element is automatically generated by MyBatis Generator, do not modify.
      This element was generated on Mon Jun 04 11:04:34 CST 2018.
    -->
    delete from t_order
    where id = #{id,jdbcType=BIGINT}
  </delete>
  <delete id="deleteByExample" parameterType="com.doushabao.saas.pojo.order.OrderExample">
    <!--
      WARNING - @mbg.generated
      This element is automatically generated by MyBatis Generator, do not modify.
      This element was generated on Mon Jun 04 11:04:34 CST 2018.
    -->
    delete from t_order
    <if test="_parameter != null">
      <include refid="Example_Where_Clause" />
    </if>
  </delete>
  <insert id="insert" parameterType="com.doushabao.saas.pojo.order.Order">
    <!--
      WARNING - @mbg.generated
      This element is automatically generated by MyBatis Generator, do not modify.
      This element was generated on Mon Jun 04 11:04:34 CST 2018.
    -->
    insert into t_order (id, ticket_no, product_id_list, 
      status, original_amount, discount_amount, 
      order_time, pay_time, source, 
      user_id, name, phone_no, 
      id_card, sex, currency, 
      is_exit, order_way, excel_batch, 
      express_no, purchas_order_no, goods_value, 
      goods_value_detail, goods_category, goods_kind, 
      goods_weight, is_Reinforce, prescription, 
      express_mark, express_time, express_line, 
      express_channel, receiver_address, loading_port, 
      destination_port, border_shopping_site, shopping_site, 
      shopping_time, premium, create_at, 
      update_at)
    values (#{id,jdbcType=BIGINT}, #{ticketNo,jdbcType=VARCHAR}, #{productIdList,jdbcType=VARCHAR}, 
      #{status,jdbcType=INTEGER}, #{originalAmount,jdbcType=INTEGER}, #{discountAmount,jdbcType=INTEGER}, 
      #{orderTime,jdbcType=TIMESTAMP}, #{payTime,jdbcType=TIMESTAMP}, #{source,jdbcType=VARCHAR}, 
      #{userId,jdbcType=BIGINT}, #{name,jdbcType=VARCHAR}, #{phoneNo,jdbcType=VARCHAR}, 
      #{idCard,jdbcType=VARCHAR}, #{sex,jdbcType=VARCHAR}, #{currency,jdbcType=VARCHAR}, 
      #{isExit,jdbcType=INTEGER}, #{orderWay,jdbcType=INTEGER}, #{excelBatch,jdbcType=VARCHAR}, 
      #{expressNo,jdbcType=VARCHAR}, #{purchasOrderNo,jdbcType=VARCHAR}, #{goodsValue,jdbcType=INTEGER}, 
      #{goodsValueDetail,jdbcType=VARCHAR}, #{goodsCategory,jdbcType=VARCHAR}, #{goodsKind,jdbcType=VARCHAR}, 
      #{goodsWeight,jdbcType=DOUBLE}, #{isReinforce,jdbcType=INTEGER}, #{prescription,jdbcType=VARCHAR}, 
      #{expressMark,jdbcType=VARCHAR}, #{expressTime,jdbcType=TIMESTAMP}, #{expressLine,jdbcType=VARCHAR}, 
      #{expressChannel,jdbcType=VARCHAR}, #{receiverAddress,jdbcType=VARCHAR}, #{loadingPort,jdbcType=VARCHAR}, 
      #{destinationPort,jdbcType=VARCHAR}, #{borderShoppingSite,jdbcType=VARCHAR}, #{shoppingSite,jdbcType=VARCHAR}, 
      #{shoppingTime,jdbcType=TIMESTAMP}, #{premium,jdbcType=INTEGER}, #{createAt,jdbcType=TIMESTAMP}, 
      #{updateAt,jdbcType=TIMESTAMP})
  </insert>
  <insert id="insertSelective" parameterType="com.doushabao.saas.pojo.order.Order">
    <!--
      WARNING - @mbg.generated
      This element is automatically generated by MyBatis Generator, do not modify.
      This element was generated on Mon Jun 04 11:04:34 CST 2018.
    -->
    insert into t_order
    <trim prefix="(" suffix=")" suffixOverrides=",">
      <if test="id != null">
        id,
      </if>
      <if test="ticketNo != null">
        ticket_no,
      </if>
      <if test="productIdList != null">
        product_id_list,
      </if>
      <if test="status != null">
        status,
      </if>
      <if test="originalAmount != null">
        original_amount,
      </if>
      <if test="discountAmount != null">
        discount_amount,
      </if>
      <if test="orderTime != null">
        order_time,
      </if>
      <if test="payTime != null">
        pay_time,
      </if>
      <if test="source != null">
        source,
      </if>
      <if test="userId != null">
        user_id,
      </if>
      <if test="name != null">
        name,
      </if>
      <if test="phoneNo != null">
        phone_no,
      </if>
      <if test="idCard != null">
        id_card,
      </if>
      <if test="sex != null">
        sex,
      </if>
      <if test="currency != null">
        currency,
      </if>
      <if test="isExit != null">
        is_exit,
      </if>
      <if test="orderWay != null">
        order_way,
      </if>
      <if test="excelBatch != null">
        excel_batch,
      </if>
      <if test="expressNo != null">
        express_no,
      </if>
      <if test="purchasOrderNo != null">
        purchas_order_no,
      </if>
      <if test="goodsValue != null">
        goods_value,
      </if>
      <if test="goodsValueDetail != null">
        goods_value_detail,
      </if>
      <if test="goodsCategory != null">
        goods_category,
      </if>
      <if test="goodsKind != null">
        goods_kind,
      </if>
      <if test="goodsWeight != null">
        goods_weight,
      </if>
      <if test="isReinforce != null">
        is_Reinforce,
      </if>
      <if test="prescription != null">
        prescription,
      </if>
      <if test="expressMark != null">
        express_mark,
      </if>
      <if test="expressTime != null">
        express_time,
      </if>
      <if test="expressLine != null">
        express_line,
      </if>
      <if test="expressChannel != null">
        express_channel,
      </if>
      <if test="receiverAddress != null">
        receiver_address,
      </if>
      <if test="loadingPort != null">
        loading_port,
      </if>
      <if test="destinationPort != null">
        destination_port,
      </if>
      <if test="borderShoppingSite != null">
        border_shopping_site,
      </if>
      <if test="shoppingSite != null">
        shopping_site,
      </if>
      <if test="shoppingTime != null">
        shopping_time,
      </if>
      <if test="premium != null">
        premium,
      </if>
      <if test="createAt != null">
        create_at,
      </if>
      <if test="updateAt != null">
        update_at,
      </if>
    </trim>
    <trim prefix="values (" suffix=")" suffixOverrides=",">
      <if test="id != null">
        #{id,jdbcType=BIGINT},
      </if>
      <if test="ticketNo != null">
        #{ticketNo,jdbcType=VARCHAR},
      </if>
      <if test="productIdList != null">
        #{productIdList,jdbcType=VARCHAR},
      </if>
      <if test="status != null">
        #{status,jdbcType=INTEGER},
      </if>
      <if test="originalAmount != null">
        #{originalAmount,jdbcType=INTEGER},
      </if>
      <if test="discountAmount != null">
        #{discountAmount,jdbcType=INTEGER},
      </if>
      <if test="orderTime != null">
        #{orderTime,jdbcType=TIMESTAMP},
      </if>
      <if test="payTime != null">
        #{payTime,jdbcType=TIMESTAMP},
      </if>
      <if test="source != null">
        #{source,jdbcType=VARCHAR},
      </if>
      <if test="userId != null">
        #{userId,jdbcType=BIGINT},
      </if>
      <if test="name != null">
        #{name,jdbcType=VARCHAR},
      </if>
      <if test="phoneNo != null">
        #{phoneNo,jdbcType=VARCHAR},
      </if>
      <if test="idCard != null">
        #{idCard,jdbcType=VARCHAR},
      </if>
      <if test="sex != null">
        #{sex,jdbcType=VARCHAR},
      </if>
      <if test="currency != null">
        #{currency,jdbcType=VARCHAR},
      </if>
      <if test="isExit != null">
        #{isExit,jdbcType=INTEGER},
      </if>
      <if test="orderWay != null">
        #{orderWay,jdbcType=INTEGER},
      </if>
      <if test="excelBatch != null">
        #{excelBatch,jdbcType=VARCHAR},
      </if>
      <if test="expressNo != null">
        #{expressNo,jdbcType=VARCHAR},
      </if>
      <if test="purchasOrderNo != null">
        #{purchasOrderNo,jdbcType=VARCHAR},
      </if>
      <if test="goodsValue != null">
        #{goodsValue,jdbcType=INTEGER},
      </if>
      <if test="goodsValueDetail != null">
        #{goodsValueDetail,jdbcType=VARCHAR},
      </if>
      <if test="goodsCategory != null">
        #{goodsCategory,jdbcType=VARCHAR},
      </if>
      <if test="goodsKind != null">
        #{goodsKind,jdbcType=VARCHAR},
      </if>
      <if test="goodsWeight != null">
        #{goodsWeight,jdbcType=DOUBLE},
      </if>
      <if test="isReinforce != null">
        #{isReinforce,jdbcType=INTEGER},
      </if>
      <if test="prescription != null">
        #{prescription,jdbcType=VARCHAR},
      </if>
      <if test="expressMark != null">
        #{expressMark,jdbcType=VARCHAR},
      </if>
      <if test="expressTime != null">
        #{expressTime,jdbcType=TIMESTAMP},
      </if>
      <if test="expressLine != null">
        #{expressLine,jdbcType=VARCHAR},
      </if>
      <if test="expressChannel != null">
        #{expressChannel,jdbcType=VARCHAR},
      </if>
      <if test="receiverAddress != null">
        #{receiverAddress,jdbcType=VARCHAR},
      </if>
      <if test="loadingPort != null">
        #{loadingPort,jdbcType=VARCHAR},
      </if>
      <if test="destinationPort != null">
        #{destinationPort,jdbcType=VARCHAR},
      </if>
      <if test="borderShoppingSite != null">
        #{borderShoppingSite,jdbcType=VARCHAR},
      </if>
      <if test="shoppingSite != null">
        #{shoppingSite,jdbcType=VARCHAR},
      </if>
      <if test="shoppingTime != null">
        #{shoppingTime,jdbcType=TIMESTAMP},
      </if>
      <if test="premium != null">
        #{premium,jdbcType=INTEGER},
      </if>
      <if test="createAt != null">
        #{createAt,jdbcType=TIMESTAMP},
      </if>
      <if test="updateAt != null">
        #{updateAt,jdbcType=TIMESTAMP},
      </if>
    </trim>
  </insert>
  <select id="countByExample" parameterType="com.doushabao.saas.pojo.order.OrderExample" resultType="java.lang.Long">
    <!--
      WARNING - @mbg.generated
      This element is automatically generated by MyBatis Generator, do not modify.
      This element was generated on Mon Jun 04 11:04:34 CST 2018.
    -->
    select count(*) from t_order
    <if test="_parameter != null">
      <include refid="Example_Where_Clause" />
    </if>
  </select>
  <update id="updateByExampleSelective" parameterType="map">
    <!--
      WARNING - @mbg.generated
      This element is automatically generated by MyBatis Generator, do not modify.
      This element was generated on Mon Jun 04 11:04:34 CST 2018.
    -->
    update t_order
    <set>
      <if test="record.id != null">
        id = #{record.id,jdbcType=BIGINT},
      </if>
      <if test="record.ticketNo != null">
        ticket_no = #{record.ticketNo,jdbcType=VARCHAR},
      </if>
      <if test="record.productIdList != null">
        product_id_list = #{record.productIdList,jdbcType=VARCHAR},
      </if>
      <if test="record.status != null">
        status = #{record.status,jdbcType=INTEGER},
      </if>
      <if test="record.originalAmount != null">
        original_amount = #{record.originalAmount,jdbcType=INTEGER},
      </if>
      <if test="record.discountAmount != null">
        discount_amount = #{record.discountAmount,jdbcType=INTEGER},
      </if>
      <if test="record.orderTime != null">
        order_time = #{record.orderTime,jdbcType=TIMESTAMP},
      </if>
      <if test="record.payTime != null">
        pay_time = #{record.payTime,jdbcType=TIMESTAMP},
      </if>
      <if test="record.source != null">
        source = #{record.source,jdbcType=VARCHAR},
      </if>
      <if test="record.userId != null">
        user_id = #{record.userId,jdbcType=BIGINT},
      </if>
      <if test="record.name != null">
        name = #{record.name,jdbcType=VARCHAR},
      </if>
      <if test="record.phoneNo != null">
        phone_no = #{record.phoneNo,jdbcType=VARCHAR},
      </if>
      <if test="record.idCard != null">
        id_card = #{record.idCard,jdbcType=VARCHAR},
      </if>
      <if test="record.sex != null">
        sex = #{record.sex,jdbcType=VARCHAR},
      </if>
      <if test="record.currency != null">
        currency = #{record.currency,jdbcType=VARCHAR},
      </if>
      <if test="record.isExit != null">
        is_exit = #{record.isExit,jdbcType=INTEGER},
      </if>
      <if test="record.orderWay != null">
        order_way = #{record.orderWay,jdbcType=INTEGER},
      </if>
      <if test="record.excelBatch != null">
        excel_batch = #{record.excelBatch,jdbcType=VARCHAR},
      </if>
      <if test="record.expressNo != null">
        express_no = #{record.expressNo,jdbcType=VARCHAR},
      </if>
      <if test="record.purchasOrderNo != null">
        purchas_order_no = #{record.purchasOrderNo,jdbcType=VARCHAR},
      </if>
      <if test="record.goodsValue != null">
        goods_value = #{record.goodsValue,jdbcType=INTEGER},
      </if>
      <if test="record.goodsValueDetail != null">
        goods_value_detail = #{record.goodsValueDetail,jdbcType=VARCHAR},
      </if>
      <if test="record.goodsCategory != null">
        goods_category = #{record.goodsCategory,jdbcType=VARCHAR},
      </if>
      <if test="record.goodsKind != null">
        goods_kind = #{record.goodsKind,jdbcType=VARCHAR},
      </if>
      <if test="record.goodsWeight != null">
        goods_weight = #{record.goodsWeight,jdbcType=DOUBLE},
      </if>
      <if test="record.isReinforce != null">
        is_Reinforce = #{record.isReinforce,jdbcType=INTEGER},
      </if>
      <if test="record.prescription != null">
        prescription = #{record.prescription,jdbcType=VARCHAR},
      </if>
      <if test="record.expressMark != null">
        express_mark = #{record.expressMark,jdbcType=VARCHAR},
      </if>
      <if test="record.expressTime != null">
        express_time = #{record.expressTime,jdbcType=TIMESTAMP},
      </if>
      <if test="record.expressLine != null">
        express_line = #{record.expressLine,jdbcType=VARCHAR},
      </if>
      <if test="record.expressChannel != null">
        express_channel = #{record.expressChannel,jdbcType=VARCHAR},
      </if>
      <if test="record.receiverAddress != null">
        receiver_address = #{record.receiverAddress,jdbcType=VARCHAR},
      </if>
      <if test="record.loadingPort != null">
        loading_port = #{record.loadingPort,jdbcType=VARCHAR},
      </if>
      <if test="record.destinationPort != null">
        destination_port = #{record.destinationPort,jdbcType=VARCHAR},
      </if>
      <if test="record.borderShoppingSite != null">
        border_shopping_site = #{record.borderShoppingSite,jdbcType=VARCHAR},
      </if>
      <if test="record.shoppingSite != null">
        shopping_site = #{record.shoppingSite,jdbcType=VARCHAR},
      </if>
      <if test="record.shoppingTime != null">
        shopping_time = #{record.shoppingTime,jdbcType=TIMESTAMP},
      </if>
      <if test="record.premium != null">
        premium = #{record.premium,jdbcType=INTEGER},
      </if>
      <if test="record.createAt != null">
        create_at = #{record.createAt,jdbcType=TIMESTAMP},
      </if>
      <if test="record.updateAt != null">
        update_at = #{record.updateAt,jdbcType=TIMESTAMP},
      </if>
    </set>
    <if test="_parameter != null">
      <include refid="Update_By_Example_Where_Clause" />
    </if>
  </update>
  <update id="updateByExample" parameterType="map">
    <!--
      WARNING - @mbg.generated
      This element is automatically generated by MyBatis Generator, do not modify.
      This element was generated on Mon Jun 04 11:04:34 CST 2018.
    -->
    update t_order
    set id = #{record.id,jdbcType=BIGINT},
      ticket_no = #{record.ticketNo,jdbcType=VARCHAR},
      product_id_list = #{record.productIdList,jdbcType=VARCHAR},
      status = #{record.status,jdbcType=INTEGER},
      original_amount = #{record.originalAmount,jdbcType=INTEGER},
      discount_amount = #{record.discountAmount,jdbcType=INTEGER},
      order_time = #{record.orderTime,jdbcType=TIMESTAMP},
      pay_time = #{record.payTime,jdbcType=TIMESTAMP},
      source = #{record.source,jdbcType=VARCHAR},
      user_id = #{record.userId,jdbcType=BIGINT},
      name = #{record.name,jdbcType=VARCHAR},
      phone_no = #{record.phoneNo,jdbcType=VARCHAR},
      id_card = #{record.idCard,jdbcType=VARCHAR},
      sex = #{record.sex,jdbcType=VARCHAR},
      currency = #{record.currency,jdbcType=VARCHAR},
      is_exit = #{record.isExit,jdbcType=INTEGER},
      order_way = #{record.orderWay,jdbcType=INTEGER},
      excel_batch = #{record.excelBatch,jdbcType=VARCHAR},
      express_no = #{record.expressNo,jdbcType=VARCHAR},
      purchas_order_no = #{record.purchasOrderNo,jdbcType=VARCHAR},
      goods_value = #{record.goodsValue,jdbcType=INTEGER},
      goods_value_detail = #{record.goodsValueDetail,jdbcType=VARCHAR},
      goods_category = #{record.goodsCategory,jdbcType=VARCHAR},
      goods_kind = #{record.goodsKind,jdbcType=VARCHAR},
      goods_weight = #{record.goodsWeight,jdbcType=DOUBLE},
      is_Reinforce = #{record.isReinforce,jdbcType=INTEGER},
      prescription = #{record.prescription,jdbcType=VARCHAR},
      express_mark = #{record.expressMark,jdbcType=VARCHAR},
      express_time = #{record.expressTime,jdbcType=TIMESTAMP},
      express_line = #{record.expressLine,jdbcType=VARCHAR},
      express_channel = #{record.expressChannel,jdbcType=VARCHAR},
      receiver_address = #{record.receiverAddress,jdbcType=VARCHAR},
      loading_port = #{record.loadingPort,jdbcType=VARCHAR},
      destination_port = #{record.destinationPort,jdbcType=VARCHAR},
      border_shopping_site = #{record.borderShoppingSite,jdbcType=VARCHAR},
      shopping_site = #{record.shoppingSite,jdbcType=VARCHAR},
      shopping_time = #{record.shoppingTime,jdbcType=TIMESTAMP},
      premium = #{record.premium,jdbcType=INTEGER},
      create_at = #{record.createAt,jdbcType=TIMESTAMP},
      update_at = #{record.updateAt,jdbcType=TIMESTAMP}
    <if test="_parameter != null">
      <include refid="Update_By_Example_Where_Clause" />
    </if>
  </update>
  <update id="updateByPrimaryKeySelective" parameterType="com.doushabao.saas.pojo.order.Order">
    <!--
      WARNING - @mbg.generated
      This element is automatically generated by MyBatis Generator, do not modify.
      This element was generated on Mon Jun 04 11:04:34 CST 2018.
    -->
    update t_order
    <set>
      <if test="ticketNo != null">
        ticket_no = #{ticketNo,jdbcType=VARCHAR},
      </if>
      <if test="productIdList != null">
        product_id_list = #{productIdList,jdbcType=VARCHAR},
      </if>
      <if test="status != null">
        status = #{status,jdbcType=INTEGER},
      </if>
      <if test="originalAmount != null">
        original_amount = #{originalAmount,jdbcType=INTEGER},
      </if>
      <if test="discountAmount != null">
        discount_amount = #{discountAmount,jdbcType=INTEGER},
      </if>
      <if test="orderTime != null">
        order_time = #{orderTime,jdbcType=TIMESTAMP},
      </if>
      <if test="payTime != null">
        pay_time = #{payTime,jdbcType=TIMESTAMP},
      </if>
      <if test="source != null">
        source = #{source,jdbcType=VARCHAR},
      </if>
      <if test="userId != null">
        user_id = #{userId,jdbcType=BIGINT},
      </if>
      <if test="name != null">
        name = #{name,jdbcType=VARCHAR},
      </if>
      <if test="phoneNo != null">
        phone_no = #{phoneNo,jdbcType=VARCHAR},
      </if>
      <if test="idCard != null">
        id_card = #{idCard,jdbcType=VARCHAR},
      </if>
      <if test="sex != null">
        sex = #{sex,jdbcType=VARCHAR},
      </if>
      <if test="currency != null">
        currency = #{currency,jdbcType=VARCHAR},
      </if>
      <if test="isExit != null">
        is_exit = #{isExit,jdbcType=INTEGER},
      </if>
      <if test="orderWay != null">
        order_way = #{orderWay,jdbcType=INTEGER},
      </if>
      <if test="excelBatch != null">
        excel_batch = #{excelBatch,jdbcType=VARCHAR},
      </if>
      <if test="expressNo != null">
        express_no = #{expressNo,jdbcType=VARCHAR},
      </if>
      <if test="purchasOrderNo != null">
        purchas_order_no = #{purchasOrderNo,jdbcType=VARCHAR},
      </if>
      <if test="goodsValue != null">
        goods_value = #{goodsValue,jdbcType=INTEGER},
      </if>
      <if test="goodsValueDetail != null">
        goods_value_detail = #{goodsValueDetail,jdbcType=VARCHAR},
      </if>
      <if test="goodsCategory != null">
        goods_category = #{goodsCategory,jdbcType=VARCHAR},
      </if>
      <if test="goodsKind != null">
        goods_kind = #{goodsKind,jdbcType=VARCHAR},
      </if>
      <if test="goodsWeight != null">
        goods_weight = #{goodsWeight,jdbcType=DOUBLE},
      </if>
      <if test="isReinforce != null">
        is_Reinforce = #{isReinforce,jdbcType=INTEGER},
      </if>
      <if test="prescription != null">
        prescription = #{prescription,jdbcType=VARCHAR},
      </if>
      <if test="expressMark != null">
        express_mark = #{expressMark,jdbcType=VARCHAR},
      </if>
      <if test="expressTime != null">
        express_time = #{expressTime,jdbcType=TIMESTAMP},
      </if>
      <if test="expressLine != null">
        express_line = #{expressLine,jdbcType=VARCHAR},
      </if>
      <if test="expressChannel != null">
        express_channel = #{expressChannel,jdbcType=VARCHAR},
      </if>
      <if test="receiverAddress != null">
        receiver_address = #{receiverAddress,jdbcType=VARCHAR},
      </if>
      <if test="loadingPort != null">
        loading_port = #{loadingPort,jdbcType=VARCHAR},
      </if>
      <if test="destinationPort != null">
        destination_port = #{destinationPort,jdbcType=VARCHAR},
      </if>
      <if test="borderShoppingSite != null">
        border_shopping_site = #{borderShoppingSite,jdbcType=VARCHAR},
      </if>
      <if test="shoppingSite != null">
        shopping_site = #{shoppingSite,jdbcType=VARCHAR},
      </if>
      <if test="shoppingTime != null">
        shopping_time = #{shoppingTime,jdbcType=TIMESTAMP},
      </if>
      <if test="premium != null">
        premium = #{premium,jdbcType=INTEGER},
      </if>
      <if test="createAt != null">
        create_at = #{createAt,jdbcType=TIMESTAMP},
      </if>
      <if test="updateAt != null">
        update_at = #{updateAt,jdbcType=TIMESTAMP},
      </if>
    </set>
    where id = #{id,jdbcType=BIGINT}
  </update>
  <update id="updateByPrimaryKey" parameterType="com.doushabao.saas.pojo.order.Order">
    <!--
      WARNING - @mbg.generated
      This element is automatically generated by MyBatis Generator, do not modify.
      This element was generated on Mon Jun 04 11:04:34 CST 2018.
    -->
    update t_order
    set ticket_no = #{ticketNo,jdbcType=VARCHAR},
      product_id_list = #{productIdList,jdbcType=VARCHAR},
      status = #{status,jdbcType=INTEGER},
      original_amount = #{originalAmount,jdbcType=INTEGER},
      discount_amount = #{discountAmount,jdbcType=INTEGER},
      order_time = #{orderTime,jdbcType=TIMESTAMP},
      pay_time = #{payTime,jdbcType=TIMESTAMP},
      source = #{source,jdbcType=VARCHAR},
      user_id = #{userId,jdbcType=BIGINT},
      name = #{name,jdbcType=VARCHAR},
      phone_no = #{phoneNo,jdbcType=VARCHAR},
      id_card = #{idCard,jdbcType=VARCHAR},
      sex = #{sex,jdbcType=VARCHAR},
      currency = #{currency,jdbcType=VARCHAR},
      is_exit = #{isExit,jdbcType=INTEGER},
      order_way = #{orderWay,jdbcType=INTEGER},
      excel_batch = #{excelBatch,jdbcType=VARCHAR},
      express_no = #{expressNo,jdbcType=VARCHAR},
      purchas_order_no = #{purchasOrderNo,jdbcType=VARCHAR},
      goods_value = #{goodsValue,jdbcType=INTEGER},
      goods_value_detail = #{goodsValueDetail,jdbcType=VARCHAR},
      goods_category = #{goodsCategory,jdbcType=VARCHAR},
      goods_kind = #{goodsKind,jdbcType=VARCHAR},
      goods_weight = #{goodsWeight,jdbcType=DOUBLE},
      is_Reinforce = #{isReinforce,jdbcType=INTEGER},
      prescription = #{prescription,jdbcType=VARCHAR},
      express_mark = #{expressMark,jdbcType=VARCHAR},
      express_time = #{expressTime,jdbcType=TIMESTAMP},
      express_line = #{expressLine,jdbcType=VARCHAR},
      express_channel = #{expressChannel,jdbcType=VARCHAR},
      receiver_address = #{receiverAddress,jdbcType=VARCHAR},
      loading_port = #{loadingPort,jdbcType=VARCHAR},
      destination_port = #{destinationPort,jdbcType=VARCHAR},
      border_shopping_site = #{borderShoppingSite,jdbcType=VARCHAR},
      shopping_site = #{shoppingSite,jdbcType=VARCHAR},
      shopping_time = #{shoppingTime,jdbcType=TIMESTAMP},
      premium = #{premium,jdbcType=INTEGER},
      create_at = #{createAt,jdbcType=TIMESTAMP},
      update_at = #{updateAt,jdbcType=TIMESTAMP}
    where id = #{id,jdbcType=BIGINT}
  </update>
</mapper>